LICENSE
MANIFEST.in
README.rst
setup.py
./qiita/__init__.py
./qiita/client.py
./qiita/exceptions.py
./qiita/items.py
./qiita/tags.py
./qiita/users.py
docs/Makefile
docs/conf.py
docs/index.rst
docs/make.bat
docs/_themes/flask/layout.html
docs/_themes/flask/relations.html
docs/_themes/flask/theme.conf
docs/_themes/flask/static/flasky.css_t
docs/_themes/flask/static/small_flask.css
qiita.egg-info/PKG-INFO
qiita.egg-info/SOURCES.txt
qiita.egg-info/dependency_links.txt
qiita.egg-info/requires.txt
qiita.egg-info/top_level.txt